README.rst
setup.py
django_registration_rest_framework.egg-info/PKG-INFO
django_registration_rest_framework.egg-info/SOURCES.txt
django_registration_rest_framework.egg-info/dependency_links.txt
django_registration_rest_framework.egg-info/requires.txt
django_registration_rest_framework.egg-info/top_level.txt
registration_api/__init__.py
registration_api/models.py
registration_api/serializers.py
registration_api/tests.py
registration_api/urls.py
registration_api/utils.py
registration_api/views.py
tests/__init__.py
tests/runtests.py
tests/settings.py