Metadata-Version: 1.1
Name: django-registration-rest-framework
Version: 0.2.4
Summary: ('Clone of Django Resgistration flow for Django Rest Framework',)
Home-page: https://github.com/tucarga/django-registration-rest-framework
Author: Alejandro Varas
Author-email: alej0varas@gmail.com
License: GPL
Keywords: django registration rest framework
Platform: UNKNOWN
Classifier: Development Status :: 1 - Planning
Classifier: Intended Audience :: Developers
Classifier: Framework :: Django
Classifier: Operating System :: POSIX :: Linux
Classifier: Programming Language :: Python
Classifier: Natural Language :: English
Classifier: License :: OSI Approved :: GNU General Public License v3 or later (GPLv3+)
Classifier: Topic :: Software Development :: Libraries
Requires: djangorestframework
